logger2telegram/__init__.py
logger2telegram/logger2tlg.py
logger2telegram-1.0.1.dist-info/LICENSE.txt
logger2telegram-1.0.1.dist-info/METADATA
logger2telegram-1.0.1.dist-info/WHEEL
logger2telegram-1.0.1.dist-info/top_level.txt
logger2telegram-1.0.1.dist-info/RECORD
