Metadata-Version: 2.1
Name: logger2telegram
Version: 1.0.1
Summary: Telegram bot logger that sends strings to telegram chat
Home-page: https://github.com/bauyrzhanospan/telegram_logger
Author: Bauyrzhan Ospan, CEO "Cleverest Technologies LLP"
Author-email: main@cleverest.tech
License: MIT
Platform: Any
Classifier: Development Status :: 5 - Production/Stable
Classifier: Intended Audience :: Developers
Classifier: License :: OSI Approved :: MIT License
Classifier: Operating System :: OS Independent
Classifier: Topic :: Software Development :: Debuggers
Classifier: Topic :: Software Development :: Libraries :: Python Modules
Classifier: Programming Language :: Python :: 3
Classifier: Programming Language :: Python :: 3.9
License-File: LICENSE.txt
